sachin_chess_utils/__init__.py
sachin_chess_utils/main.py
sachin_chess_utils/move.py
sachin_chess_utils-0.1.5.dist-info/METADATA
sachin_chess_utils-0.1.5.dist-info/WHEEL
sachin_chess_utils-0.1.5.dist-info/entry_points.txt
sachin_chess_utils-0.1.5.dist-info/top_level.txt
sachin_chess_utils-0.1.5.dist-info/RECORD
