Metadata-Version: 2.1
Name: sachin-chess-utils
Version: 0.1.5
Summary: UNKNOWN
Home-page: UNKNOWN
Author: Sachin Chauhan Infocusp
License: UNKNOWN
Platform: UNKNOWN
Requires-Dist: chess (==1.11.2)
